fast_cache/__init__.py
fast_cache/integration.py
fast_cache/backends/__init__.py
fast_cache/backends/backend.py
fast_cache/backends/dynamodb.py
fast_cache/backends/google_firestore.py
fast_cache/backends/memcached.py
fast_cache/backends/memory.py
fast_cache/backends/mongodb.py
fast_cache/backends/postgres.py
fast_cache/backends/redis.py
fastapi_cachekit-0.1.5.dist-info/licenses/LICENSE.md
fastapi_cachekit-0.1.5.dist-info/METADATA
fastapi_cachekit-0.1.5.dist-info/WHEEL
fastapi_cachekit-0.1.5.dist-info/top_level.txt
fastapi_cachekit-0.1.5.dist-info/RECORD
