Metadata-Version: 2.4
Name: fastapi-cachekit
Version: 0.1.5
Summary: High-performance caching solution for FastAPI applications
Author-email: Bijay Nayak <bijay6779@gmail.com>
License-Expression: MIT
Project-URL: Homepage, https://github.com/devbijay/fast-cache
Project-URL: Documentation, https://devbijay.github.io/Fast-Cache/
Project-URL: Repository, https://github.com/devbijay/fast-cache.git
Project-URL: Issues, https://github.com/devbijay/fast-cache/issues
Keywords: fastapi,cache,redis,async,python,starlette,asyncio
Classifier: Development Status :: 4 - Beta
Classifier: Framework :: FastAPI
Classifier: Intended Audience :: Developers
Classifier: Operating System :: OS Independent
Classifier: Programming Language :: Python :: 3.9
Classifier: Programming Language :: Python :: 3.10
Classifier: Programming Language :: Python :: 3.11
Classifier: Programming Language :: Python :: 3.12
Classifier: Programming Language :: Python :: 3.13
Classifier: Topic :: Software Development :: Libraries :: Python Modules
Classifier: Topic :: Internet :: WWW/HTTP
Classifier: Topic :: Internet :: WWW/HTTP :: Dynamic Content
Classifier: Topic :: Software Development :: Libraries
Classifier: Topic :: Utilities
Classifier: Typing :: Typed
Requires-Python: >=3.9
License-File: LICENSE.md
Requires-Dist: fastapi>=0.75.0
Requires-Dist: apscheduler>=3.4.0
Provides-Extra: redis
Requires-Dist: redis>=4.2.0; extra == "redis"
Provides-Extra: postgres
Requires-Dist: psycopg[pool]>=3.2.9; extra == "postgres"
Provides-Extra: memcached
Requires-Dist: aiomcache>=0.8.1; extra == "memcached"
Requires-Dist: pymemcache>=4.0.0; extra == "memcached"
Provides-Extra: mongodb
Requires-Dist: pymongo[gssapi,snappy]>=4.6.0; extra == "mongodb"
Provides-Extra: firestore
Requires-Dist: google-cloud-firestore>=2.3.0; extra == "firestore"
Provides-Extra: dynamodb
Requires-Dist: boto3>=1.10.0; extra == "dynamodb"
Requires-Dist: aioboto3>=6.0.0; extra == "dynamodb"
Provides-Extra: all
Requires-Dist: redis>=4.2.0; extra == "all"
Requires-Dist: psycopg[pool]>=3.2.9; extra == "all"
Requires-Dist: apscheduler>=3.4.0; extra == "all"
Requires-Dist: aiomcache>=0.8.1; extra == "all"
Requires-Dist: pymemcache>=4.0.0; extra == "all"
Requires-Dist: pymongo[gssapi,snappy,srv]>=4.6.0; extra == "all"
Requires-Dist: google-cloud-firestore>=2.3.0; extra == "all"
Requires-Dist: boto3>=1.10.0; extra == "all"
Requires-Dist: aioboto3>=6.0.0; extra == "all"
Dynamic: license-file
